signedjson/__init__.py
signedjson/key.py
signedjson/py.typed
signedjson/sign.py
signedjson/types.py
signedjson-1.1.3.dist-info/LICENSE
signedjson-1.1.3.dist-info/METADATA
signedjson-1.1.3.dist-info/WHEEL
signedjson-1.1.3.dist-info/top_level.txt
signedjson-1.1.3.dist-info/RECORD
