Metadata-Version: 2.1
Name: signedjson
Version: 1.1.3
Summary: Sign JSON with Ed25519 signatures
License: UNKNOWN
Keywords: json
Platform: UNKNOWN
License-File: LICENSE
Requires-Dist: canonicaljson (>=1.0.0)
Requires-Dist: unpaddedbase64 (>=1.0.1)
Requires-Dist: pynacl (>=0.3.0)
Requires-Dist: typing (>=3.5) ; python_version < "3.5"
Requires-Dist: typing-extensions (>=3.5) ; python_version < "3.8"
Requires-Dist: importlib-metadata ; python_version < "3.8"
Provides-Extra: dev
Requires-Dist: typing-extensions (>=3.5) ; extra == 'dev'
